README.md
setup.py
rambler_kassa/__init__.py
rambler_kassa/exceptions.py
rambler_kassa/rambler_kassa.py
rambler_kassa/request_manager.py
rambler_kassa/utils.py
rambler_kassa.egg-info/PKG-INFO
rambler_kassa.egg-info/SOURCES.txt
rambler_kassa.egg-info/dependency_links.txt
rambler_kassa.egg-info/requires.txt
rambler_kassa.egg-info/top_level.txt
rambler_kassa/models/__init__.py
rambler_kassa/models/movie.py
rambler_kassa/models/schedule.py