Metadata-Version: 2.1
Name: rambler-kassa
Version: 0.0.5
Summary: API Rambler Kassa
Home-page: https://github.com/NMelis/rambler-kassa
Author: NMelis
Maintainer: NMelis
License: MIT
Platform: UNKNOWN
Classifier: Development Status :: 4 - Beta
Classifier: Operating System :: OS Independent
Classifier: Intended Audience :: Developers
Classifier: Programming Language :: Python
Classifier: Programming Language :: Python :: 3
Classifier: Programming Language :: Python :: 3.4
Classifier: Programming Language :: Python :: 3.5
Classifier: Programming Language :: Python :: 3.6
Classifier: Topic :: Software Development :: Libraries
